easy_yfinance/__init__.py
easy_yfinance/core.py
easy_yfinance/plotting.py
easy_yfinance-0.1.0.dist-info/licenses/LICENSE
easy_yfinance-0.1.0.dist-info/METADATA
easy_yfinance-0.1.0.dist-info/WHEEL
easy_yfinance-0.1.0.dist-info/top_level.txt
easy_yfinance-0.1.0.dist-info/RECORD
